singpass_client/__init__.py
singpass_client/client.py
singpass_client/exceptions.py
singpass_client/helpers.py
singpass_client-0.1.2.dist-info/METADATA
singpass_client-0.1.2.dist-info/WHEEL
singpass_client-0.1.2.dist-info/entry_points.txt
singpass_client-0.1.2.dist-info/licenses/LICENSE
singpass_client-0.1.2.dist-info/RECORD
