Metadata-Version: 2.4
Name: singpass-client
Version: 0.1.2
Summary: Add your description here
Author-email: khinyu <khinyu2000@gmail.com>
License-Expression: MIT
License-File: LICENSE
Requires-Python: >=3.10
Requires-Dist: httpx>=0.28.1
Requires-Dist: joserfc>=1.0.4
